[
  {
    "Name": "T1",
    "Time": "02/13/2023 12:46:30",
    "CurrentState": "Inactive",
    "TotalFilesToCopy": "",
    "TotalFilesSizeToCopy": "",
    "NbFilesLeft": "",
    "FilesSizeLeft": "",
    "FilePath": "",
    "FileDestinationPath": ""
  },
  {
    "Name": "T2",
    "Time": "02/13/2023 12:46:30",
    "CurrentState": "Inactive",
    "TotalFilesToCopy": "",
    "TotalFilesSizeToCopy": "",
    "NbFilesLeft": "",
    "FilesSizeLeft": "",
    "FilePath": "",
    "FileDestinationPath": ""
  }
]
